pytrms/__init__.py
pytrms/_base/__init__.py
pytrms/_base/ioniclient.py
pytrms/_base/mqttclient.py
pytrms/_version.py
pytrms/clients/__init__.py
pytrms/clients/db_api.py
pytrms/clients/dummy.py
pytrms/clients/ioniclient.py
pytrms/clients/modbus.py
pytrms/clients/mqtt.py
pytrms/clients/ssevent.py
pytrms/compose/__init__.py
pytrms/compose/composition.py
pytrms/data/IoniTofPrefs.ini
pytrms/data/ParaIDs.csv
pytrms/helpers.py
pytrms/instrument.py
pytrms/measurement.py
pytrms/peaktable.py
pytrms/plotting/__init__.py
pytrms/plotting/plotting.py
pytrms/readers/__init__.py
pytrms/readers/ionitof_reader.py
pytrms-0.9.9.dist-info/LICENSE
pytrms-0.9.9.dist-info/METADATA
pytrms-0.9.9.dist-info/WHEEL
pytrms-0.9.9.dist-info/RECORD
