Metadata-Version: 2.3
Name: pytrms
Version: 0.9.9
Summary: Python bundle for proton-transfer reaction mass-spectrometry (PTR-MS).
License: GPL-2.0
Author: Moritz Koenemann
Author-email: moritz.koenemann@ionicon.com
Requires-Python: >=3.10,<4.0
Classifier: License :: OSI Approved :: GNU General Public License v2 (GPLv2)
Classifier: Programming Language :: Python :: 3
Classifier: Programming Language :: Python :: 3.10
Classifier: Programming Language :: Python :: 3.11
Classifier: Programming Language :: Python :: 3.12
Classifier: Programming Language :: Python :: 3.13
Requires-Dist: h5py (>=3.12.1,<4.0.0)
Requires-Dist: matplotlib (>=3.9.2,<4.0.0)
Requires-Dist: paho-mqtt (>=1.6.1,<3.0)
Requires-Dist: pandas (>=2.2.3,<3.0.0)
Requires-Dist: pyModbusTCP (>=0.1.9)
Requires-Dist: requests (>=2.32.3,<3.0.0)
